Metadata-Version: 2.1
Name: whitecore
Version: 0.1
Summary: This is an interpretation of your programming language
Home-page: UNKNOWN
Author-email: sup.harzi@gmail.com
License: UNKNOWN
Platform: UNKNOWN
License-File: LICENSE
